{
	"backtrace" : 0,
	"backtraceGraph" : 
	{
		"commands" : [],
		"files" : 
		[
			"CMakeLists.txt"
		],
		"nodes" : 
		[
			{
				"file" : 0
			}
		]
	},
	"dependencies" : 
	[
		{
			"id" : "MyApp_autogen_timestamp_deps::@6890427a1f51a3e7e1df"
		}
	],
	"id" : "MyApp_autogen::@6890427a1f51a3e7e1df",
	"isGeneratorProvided" : true,
	"name" : "MyApp_autogen",
	"paths" : 
	{
		"build" : ".",
		"source" : "."
	},
	"sourceGroups" : 
	[
		{
			"name" : "",
			"sourceIndexes" : 
			[
				0
			]
		},
		{
			"name" : "CMake Rules",
			"sourceIndexes" : 
			[
				1,
				2
			]
		}
	],
	"sources" : 
	[
		{
			"backtrace" : 0,
			"isGenerated" : true,
			"path" : "B:/c++/SkillTusk/36 \u0412\u0438\u0434\u0436\u0435\u0442\u044b Qt/build-task-1-Desktop_Qt_5_15_2_MinGW_64_bit-Debug/CMakeFiles/MyApp_autogen",
			"sourceGroupIndex" : 0
		},
		{
			"backtrace" : 0,
			"isGenerated" : true,
			"path" : "B:/c++/SkillTusk/36 \u0412\u0438\u0434\u0436\u0435\u0442\u044b Qt/build-task-1-Desktop_Qt_5_15_2_MinGW_64_bit-Debug/CMakeFiles/MyApp_autogen.rule",
			"sourceGroupIndex" : 1
		},
		{
			"backtrace" : 0,
			"isGenerated" : true,
			"path" : "B:/c++/SkillTusk/36 \u0412\u0438\u0434\u0436\u0435\u0442\u044b Qt/build-task-1-Desktop_Qt_5_15_2_MinGW_64_bit-Debug/MyApp_autogen/timestamp.rule",
			"sourceGroupIndex" : 1
		}
	],
	"type" : "UTILITY"
}
