{
	"configurations" : 
	[
		{
			"directories" : 
			[
				{
					"build" : ".",
					"jsonFile" : "directory-.-Debug-d0094a50bb2071803777.json",
					"minimumCMakeVersion" : 
					{
						"string" : "3.27"
					},
					"projectIndex" : 0,
					"source" : ".",
					"targetIndexes" : 
					[
						0,
						1,
						2
					]
				}
			],
			"name" : "Debug",
			"projects" : 
			[
				{
					"directoryIndexes" : 
					[
						0
					],
					"name" : "SoundButton",
					"targetIndexes" : 
					[
						0,
						1,
						2
					]
				}
			],
			"targets" : 
			[
				{
					"directoryIndex" : 0,
					"id" : "SoundButton::@6890427a1f51a3e7e1df",
					"jsonFile" : "target-SoundButton-Debug-fa2c3046c252982496fb.json",
					"name" : "SoundButton",
					"projectIndex" : 0
				},
				{
					"directoryIndex" : 0,
					"id" : "SoundButton_autogen::@6890427a1f51a3e7e1df",
					"jsonFile" : "target-SoundButton_autogen-Debug-bbb3dd38764803d08205.json",
					"name" : "SoundButton_autogen",
					"projectIndex" : 0
				},
				{
					"directoryIndex" : 0,
					"id" : "SoundButton_autogen_timestamp_deps::@6890427a1f51a3e7e1df",
					"jsonFile" : "target-SoundButton_autogen_timestamp_deps-Debug-d004c9882e474d90ee9d.json",
					"name" : "SoundButton_autogen_timestamp_deps",
					"projectIndex" : 0
				}
			]
		}
	],
	"kind" : "codemodel",
	"paths" : 
	{
		"build" : "B:/c++/SkillTusk/38-NewQt/build-SoundButton-Desktop_Qt_5_15_2_MinGW_64_bit-Debug",
		"source" : "B:/c++/SkillTusk/38-NewQt/SoundButton"
	},
	"version" : 
	{
		"major" : 2,
		"minor" : 6
	}
}
